{
  "routes": [
    {
      "id": "volta-negra-centro",
      "title": "Caminhada Volta Negra — Centro",
      "color": "#E91E63",
      "stops": [
        { "name": "Largo da Memória",       "coord": [-46.640042, -23.547813] },
        { "name": "Largo São Francisco",    "coord": [-46.637000, -23.549757] },
        { "name": "Largo da Misericórdia",  "coord": [-46.634595, -23.548486] },
        { "name": "Praça Antônio Prado",    "coord": [-46.634537, -23.545617] }
      ],
      "path": {
        "type": "Feature",
        "properties": {},
        "geometry": {
          "type": "LineString",
          "coordinates": [
            [-46.640042, -23.547813],
            [-46.637000, -23.549757],
            [-46.634595, -23.548486],
            [-46.634537, -23.545617]
          ]
        }
      }
    }
  ]
}
